Metadata-Version: 2.1
Name: test-sentry-dingtalk
Version: 1.0.8
Summary: A Sentry extension which integrates with Dingtalk robot. test
Home-page: https://code.aliyun.com/PlayGoods-Materiel/wanwu-senstry-dingtalk.git
Author: dazao
Author-email: zhaodazao@gmail.com
License: BSD
Keywords: test-sentry-dingtalk
Platform: any
Classifier: Framework :: Django
Classifier: Intended Audience :: Developers
Classifier: Intended Audience :: System Administrators
Classifier: Operating System :: OS Independent
Classifier: Topic :: Software Development
Provides-Extra: test
